bubblemask/__init__.py
bubblemask/__main__.py
bubblemask/apply.py
bubblemask/build.py
bubblemask/mask.py
bubblemask-1.0.1.dist-info/LICENSE
bubblemask-1.0.1.dist-info/METADATA
bubblemask-1.0.1.dist-info/WHEEL
bubblemask-1.0.1.dist-info/top_level.txt
bubblemask-1.0.1.dist-info/RECORD
