Metadata-Version: 2.2
Name: bubblemask
Version: 1.0.1
Summary: Package for applying Gaussian 'Bubbles' masks to images.
Author-email: "Jack E. Taylor" <Taylor@psych.uni-frankfurt.de>
Project-URL: Homepage, https://github.com/JackEdTaylor/bubblemask
Project-URL: Issues, https://github.com/JackEdTaylor/bubblemask/issues
Classifier: Programming Language :: Python :: 3
Classifier: Operating System :: OS Independent
Classifier: License :: OSI Approved :: GNU General Public License v3 (GPLv3)
Requires-Python: >=3.9
License-File: LICENSE
Requires-Dist: numpy>=2.0
Requires-Dist: Pillow>=10.0.1
Requires-Dist: scikit-image>=0.19.3
Requires-Dist: scipy>=1.13.0
